closedcv/__init__.py
closedcv/libfunctions.py
ClosedCV-1.0.7.dist-info/LICENSE
ClosedCV-1.0.7.dist-info/METADATA
ClosedCV-1.0.7.dist-info/WHEEL
ClosedCV-1.0.7.dist-info/top_level.txt
ClosedCV-1.0.7.dist-info/RECORD
