Metadata-Version: 2.1
Name: ClosedCV
Version: 1.0.7
Summary: Like a certain other CV but closed!
Home-page: https://github.com/EitherOr6917/ClosedCV
Author: Isaac Nelson
Project-URL: Bug Tracker, https://github.com/EitherOr6917/ClosedCV/issues
Classifier: Programming Language :: Python :: 3
Classifier: License :: OSI Approved :: MIT License
Classifier: Operating System :: OS Independent
Requires-Python: >=3.9
License-File: LICENSE
